covid_19/__init__.py
covid_19/api.py
covid_19/data.py
covid_19/utils.py
covid_19/wsgi.py
covid_19-0.5.0.dist-info/entry_points.txt
covid_19-0.5.0.dist-info/WHEEL
covid_19-0.5.0.dist-info/METADATA
covid_19-0.5.0.dist-info/RECORD
