Metadata-Version: 2.1
Name: covid-19
Version: 0.5.0
Summary: An API around the https://github.com/CSSEGISandData/COVID-19 dataset
Home-page: https://coronavirus-api.net
License: Apache-2.0
Keywords: coronavirus,covid,covid19,covid-19
Author: Stephan Fitzpatrick
Author-email: knowsuchagency@gmail.com
Requires-Python: >=3.7,<4.0
Classifier: License :: OSI Approved :: Apache Software License
Classifier: Programming Language :: Python :: 3
Classifier: Programming Language :: Python :: 3.7
Classifier: Programming Language :: Python :: 3.8
Requires-Dist: hug (>=2.6.1,<3.0.0)
Requires-Dist: pandas (>=1.0.3,<2.0.0)
Requires-Dist: requests (>=2.23.0,<3.0.0)
Project-URL: Repository, https://github.com/knowsuchagency/covid-19
